cloopui_server/__init__.py
cloopui_server/__main__.py
cloopui_server/command_line.py
cloopui_server-0.7.dist-info/METADATA
cloopui_server-0.7.dist-info/WHEEL
cloopui_server-0.7.dist-info/entry_points.txt
cloopui_server-0.7.dist-info/top_level.txt
cloopui_server-0.7.dist-info/RECORD
