Metadata-Version: 2.1
Name: cloopui-server
Version: 0.7
Summary: Fast DB handler
Home-page: https://catalyseur.ca
Author: Francis B. Lavoie
Author-email: francis.b.lavoie@usherbrooke.ca
License: UNKNOWN
Platform: UNKNOWN
Classifier: Programming Language :: Python :: 3
Classifier: License :: OSI Approved :: MIT License
Classifier: Operating System :: OS Independent
Requires-Dist: mariadb
Requires-Dist: pyodbc
